gailbot/README.md
gailbot/__init__.py
gailbot/api.py
gailbot/api.spec
gailbot/__pycache__/__init__.cpython-310.pyc
gailbot/__pycache__/api.cpython-310.pyc
gailbot/config_backend/__init__.py
gailbot/config_backend/paths.toml
gailbot/config_backend/__pycache__/__init__.cpython-310.pyc
gailbot/config_backend/engines/google/google_config.toml
gailbot/config_backend/engines/watson/watson_config.toml
gailbot/config_backend/engines/whisper/whisper_config.toml
gailbot/config_backend/plugin/valid_plugin.toml
gailbot/config_backend/services/default_setting.toml
gailbot/config_backend/services/format.md
gailbot/config_backend/services/service.toml
gailbot/config_backend/settings/default.toml
gailbot/config_backend/toplevel/ws_config.toml
gailbot/config_backend/toplevel/ws_root.toml
gailbot/config_backend/util/log.toml
gailbot/configs/__init__.py
gailbot/configs/__pycache__/__init__.cpython-310.pyc
gailbot/configs/confs/__init__.py
gailbot/configs/confs/paths.py
gailbot/configs/confs/__pycache__/__init__.cpython-310.pyc
gailbot/configs/confs/__pycache__/paths.cpython-310.pyc
gailbot/configs/interfaces/__init__.py
gailbot/configs/interfaces/__pycache__/__init__.cpython-310.pyc
gailbot/configs/interfaces/config/ws_config.py
gailbot/configs/interfaces/config/__pycache__/ws_config.cpython-310.pyc
gailbot/configs/interfaces/core/engines/google.py
gailbot/configs/interfaces/core/engines/watson.py
gailbot/configs/interfaces/core/engines/whisper.py
gailbot/configs/interfaces/core/engines/__pycache__/google.cpython-310.pyc
gailbot/configs/interfaces/core/engines/__pycache__/watson.cpython-310.pyc
gailbot/configs/interfaces/core/engines/__pycache__/whisper.cpython-310.pyc
gailbot/configs/interfaces/core/setting/defaults.py
gailbot/configs/interfaces/core/setting/__pycache__/defaults.cpython-310.pyc
gailbot/configs/interfaces/core/util/logger.py
gailbot/configs/interfaces/core/util/__pycache__/logger.cpython-310.pyc
gailbot/configs/interfaces/plugin/__init__.py
gailbot-0.1.7.dist-info/licenses/LICENSE
gailbot-0.1.7.dist-info/METADATA
gailbot-0.1.7.dist-info/WHEEL
gailbot-0.1.7.dist-info/top_level.txt
gailbot-0.1.7.dist-info/RECORD
