Metadata-Version: 2.4
Name: GailBot
Version: 0.1.7
Summary: GailBot API
Author-email: Muhammad Umair <muhammad.umair@tufts.edu>
Maintainer-email: Human Interaction Lab - Tufts University <hilab-dev@elist.tufts.edu>
License: MIT License
Project-URL: homepage, https://sites.tufts.edu/hilab/gailbot-an-automatic-transcription-system-for-conversation-analysis/
Project-URL: source, https://github.com/mumair01/GailBot
Project-URL: tracker, https://github.com/mumair01/GailBot/issues
Classifier: Intended Audience :: Science/Research
Classifier: Programming Language :: Python
Classifier: Programming Language :: Python :: 3
Classifier: Programming Language :: Python :: 3.10
Classifier: Topic :: Scientific/Engineering
Classifier: Operating System :: MacOS
Requires-Python: >=3.10
License-File: LICENSE
Requires-Dist: pydantic==2.5.1
Requires-Dist: psutil==5.9.4
Requires-Dist: userpaths==0.1.3
Requires-Dist: dict_to_dataclass==0.0.8
Requires-Dist: toml==0.10.2
Requires-Dist: requests==2.28.2
Requires-Dist: pydub==0.25.1
Requires-Dist: moviepy==1.0.3
Requires-Dist: google-api-core==2.11.0
Requires-Dist: google-cloud-speech==2.18.0
Requires-Dist: ibm-cloud-sdk-core==3.16.2
Requires-Dist: ibm-watson==7.0.0
Requires-Dist: torch==2.0.1
Requires-Dist: openai-whisper==20230314
Requires-Dist: faster-whisper==1.0.0
Requires-Dist: whisper-timestamped==1.14.1
Requires-Dist: torchvision==0.15.2
Requires-Dist: boto3==1.26.105
Requires-Dist: botocore==1.29.105
Requires-Dist: cryptography
Requires-Dist: syllables==1.0.7
Requires-Dist: tqdm==4.66.2
Requires-Dist: pytz
Requires-Dist: contourpy>=1.0.1
Requires-Dist: fonttools>=4.22.0
Requires-Dist: pyparsing>=2.3.1
Requires-Dist: pandas>=0.19
Requires-Dist: typer[all]>=0.2.1
Requires-Dist: pandas>=0.19
Requires-Dist: librosa>=0.6.0
Requires-Dist: torch-pitch-shift>=1.2.2
Requires-Dist: torchaudio>=0.7.0
Requires-Dist: pyloudnorm==0.1.0
Provides-Extra: dev
Requires-Dist: pytest; extra == "dev"
Requires-Dist: pytest-cov; extra == "dev"
Requires-Dist: pytest-timeout; extra == "dev"
Requires-Dist: pytest-xdist; extra == "dev"
Requires-Dist: ipython; extra == "dev"
Dynamic: license-file
